config/settings/__init__.py
config/settings/test.py
django_coturn/__init__.py
django_coturn/admin.py
django_coturn/apps.py
django_coturn/enum.py
django_coturn/models.py
django_coturn/services.py
django_coturn/settings.py
django_coturn/signals.py
django_coturn/urls.py
django_coturn/views.py
django_coturn/management/__init__.py
django_coturn/management/commands/__init__.py
django_coturn/management/commands/coturn_sync.py
django_coturn/migrations/0001_initial.py
django_coturn/migrations/__init__.py
tests/apps/testapp/models.py
tests/apps/testapp/migrations/0001_initial.py
tests/apps/testapp/migrations/__init__.py
django_coturn-0.3.1.dist-info/LICENSE
django_coturn-0.3.1.dist-info/METADATA
django_coturn-0.3.1.dist-info/WHEEL
django_coturn-0.3.1.dist-info/top_level.txt
django_coturn-0.3.1.dist-info/zip-safe
django_coturn-0.3.1.dist-info/RECORD
