Metadata-Version: 2.1
Name: django-coturn
Version: 0.3.1
Summary: Django Coturn is a Django app to synchronize django admins/users with Coturn's user database.         Coturn is an open-source STUN/TURN/ICE server.
Home-page: http://github.com/bitsy-ai/django-coturn
Author: Leigh Johnson
Author-email: leigh@bitsy.ai
License: GNU AGPLv3
Keywords: django stun turn ice coturn webrtc
Platform: UNKNOWN
Classifier: Programming Language :: Python :: 3.6
Classifier: Programming Language :: Python :: 3.7
Classifier: Programming Language :: Python :: 3.8
Classifier: Programming Language :: Python :: 3.9
Classifier: Framework :: Django
Classifier: Framework :: Django :: 3.1
Classifier: Framework :: Django :: 3.2
Requires-Python: >3.6.9
Requires-Dist: django (>=3.2)
Requires-Dist: psycopg2
